peasoup/uploadlogs.py
peasoup/__init__.py
peasoup/peasoup.py
peasoup/util.py
peasoup/pidutil.py
peasoup/errors.py
peasoup/restart.py
peasoup/gui/__init__.py
peasoup/gui/uploader.py
peasoup/gui/util.py
peasoup/gui/restarter.py
peasoup-0.1.1.dist-info/RECORD
peasoup-0.1.1.dist-info/METADATA
peasoup-0.1.1.dist-info/metadata.json
peasoup-0.1.1.dist-info/top_level.txt
peasoup-0.1.1.dist-info/DESCRIPTION.rst
peasoup-0.1.1.dist-info/pbr.json
peasoup-0.1.1.dist-info/WHEEL
