Metadata-Version: 2.0
Name: peasoup
Version: 0.1.1
Summary: Common tools for application deployment!
Home-page: https://github.com/timeyyy/apptools
Author: timothy eichler
Author-email: tim_eichler@hotmail.com
License: BSD3
Keywords: gui programming apptools python3 permissions deployment application
Platform: UNKNOWN
Classifier: Development Status :: 3 - Alpha
Classifier: Intended Audience :: Developers
Classifier: Topic :: Software Development :: Build Tools
Classifier: License :: OSI Approved :: BSD License
Classifier: Programming Language :: Python :: 3
Classifier: Programming Language :: Python :: 3.2
Classifier: Programming Language :: Python :: 3.3
Classifier: Programming Language :: Python :: 3.4
Classifier: Programming Language :: Python :: 3.5
